joppy/__init__.py
joppy/client_api.py
joppy/data_types.py
joppy/py.typed
joppy/server_api.py
joppy/tools.py
joppy-1.0.1.dist-info/licenses/LICENSE
joppy-1.0.1.dist-info/METADATA
joppy-1.0.1.dist-info/WHEEL
joppy-1.0.1.dist-info/top_level.txt
joppy-1.0.1.dist-info/RECORD
